torizon_io_api/__init__.py
torizon_io_api/api/__init__.py
torizon_io_api/api/device_metrics_api.py
torizon_io_api/api/devices_api.py
torizon_io_api/api/fleets_api.py
torizon_io_api/api/packages_api.py
torizon_io_api/api/remote_access_api.py
torizon_io_api/api/updates_api.py
torizon_io_api/api_client.py
torizon_io_api/api_response.py
torizon_io_api/configuration.py
torizon_io_api/exceptions.py
torizon_io_api/models/__init__.py
torizon_io_api/models/bad_request_repr.py
torizon_io_api/models/client_signature.py
torizon_io_api/models/conflict_repr.py
torizon_io_api/models/create_fleet.py
torizon_io_api/models/create_lockbox_request.py
torizon_io_api/models/create_session_request.py
torizon_io_api/models/custom_update_data.py
torizon_io_api/models/delegation_info.py
torizon_io_api/models/detailed_metric_query.py
torizon_io_api/models/device_create_req.py
torizon_io_api/models/device_id.py
torizon_io_api/models/device_info.py
torizon_io_api/models/device_info_basic.py
torizon_io_api/models/device_info_extended.py
torizon_io_api/models/device_name_request.py
torizon_io_api/models/device_notes_request.py
torizon_io_api/models/device_package.py
torizon_io_api/models/device_packages.py
torizon_io_api/models/device_packages_search_params.py
torizon_io_api/models/device_session.py
torizon_io_api/models/device_sort.py
torizon_io_api/models/device_sort_direction.py
torizon_io_api/models/device_status.py
torizon_io_api/models/ecu_info_image.py
torizon_io_api/models/ecu_info_response.py
torizon_io_api/models/edit_package.py
torizon_io_api/models/error_representation.py
torizon_io_api/models/external_package.py
torizon_io_api/models/file_info.py
torizon_io_api/models/fleet.py
torizon_io_api/models/fleet_metrics_outliers_request.py
torizon_io_api/models/fleet_metrics_outliers_response.py
torizon_io_api/models/fleet_type.py
torizon_io_api/models/hashes.py
torizon_io_api/models/image.py
torizon_io_api/models/installed_package.py
torizon_io_api/models/ip_address_request.py
torizon_io_api-0.0.7.dist-info/METADATA
torizon_io_api-0.0.7.dist-info/WHEEL
torizon_io_api-0.0.7.dist-info/RECORD
